Metadata-Version: 2.3
Name: fkask
Version: 3.1.8.dev0
Summary: A simple framework for building complex web applications.
Maintainer-email: Pallets <contact@palletsprojects.com>
Requires-Python: >=3.9
Classifier: Development Status :: 5 - Production/Stable
Classifier: Environment :: Web Environment
Classifier: Framework :: Flask
Classifier: Intended Audience :: Developers
Classifier: License :: OSI Approved :: BSD License
Classifier: Operating System :: OS Independent
Classifier: Programming Language :: Python
Classifier: Topic :: Internet :: WWW/HTTP :: Dynamic Content
Classifier: Topic :: Internet :: WWW/HTTP :: WSGI
Classifier: Topic :: Internet :: WWW/HTTP :: WSGI :: Application
Classifier: Topic :: Software Development :: Libraries :: Application Frameworks
Classifier: Typing :: Typed
Requires-Dist: Werkzeug>=3.1
Requires-Dist: Jinja2>=3.1.2
Requires-Dist: itsdangerous>=2.2
Requires-Dist: click>=8.1.3
Requires-Dist: blinker>=1.9
Requires-Dist: importlib-metadata>=3.6; python_version < '3.10'
Requires-Dist: asgiref>=3.2 ; extra == "async"
Requires-Dist: python-dotenv ; extra == "dotenv"
Project-URL: Changes, https://flask.palletsprojects.com/changes/
Project-URL: Chat, https://discord.gg/pallets
Project-URL: Documentation, https://flask.palletsprojects.com/
Project-URL: Donate, https://palletsprojects.com/donate
Project-URL: Source, https://github.com/pallets/flask/
Provides-Extra: async
Provides-Extra: dotenv
